{
    "videoTitle": "Kald alle 3 kunder - Oplev Nas i K.B. Hallen! Nas er tilbage i Danmark for at fejre 30-친rs jubil칝et for sit ikoniske debutalbum \"Illmatic\". Oplev en legende p친 scenen, n친r han indtager K.B. Hallen fredag d. 25. oktober 2024 游꿨 Som kunde hos 3 har du mulighed for at sikre dig billetter til koncerten gennem vores presale, der starter tirsdag d. 23. april kl. 10. Sid klar p친 Mit 3 og find dit link til presale 游꿞游눤",
    "url": "https://www.facebook.com/3Danmark/posts/nas-kb-hallen-2024-04-19",
    "likes": "16",
    "published": "2024-04-19",
    "dataFetchDate": "2024-12-08",
    "comments": [
        {
            "user": "3 Danmark",
            "likes": "0",
            "timestamp": "2024-04-20",
            "comment": "L칝s mere via linket her: https://www.3.dk/kampagner/presale-med-3/",
            "replies": []
        },
        {
            "user": "Anonymous",
            "likes": "0",
            "timestamp": "2024-04-20",
            "comment": "Anonymous",
            "replies": []
        },
        {
            "user": "Anonymous",
            "likes": "0",
            "timestamp": "2024-04-20",
            "comment": "Anonymous",
            "replies": []
        }
    ]
}
